{
    "model": {
        "type": "range_dispatch",
        "property": "custom_model_data",
        "fallback": {
            "type": "model",
            "model": "minecraft:item/totem_of_undying"
        },
        "entries": [
            {
                "threshold": 52,
                "model": {
                    "type": "model",
                    "model": "minecraft:item/gold_trophy"
                }
            },
            {
                "threshold": 69,
                "model": {
                    "type": "model",
                    "model": "minecraft:item/boost"
                }
            },
            {
                "threshold": 90,
                "model": {
                    "type": "model",
                    "model": "minecraft:item/cross_totem"
                }
            },
            {
                "threshold": 91,
                "model": {
                    "type": "model",
                    "model": "minecraft:item/dark_cross_totem"
                }
            },
            {
                "threshold": 92,
                "model": {
                    "type": "model",
                    "model": "minecraft:item/wither_totem"
                }
            },
            {
                "threshold": 97,
                "model": {
                    "type": "model",
                    "model": "minecraft:item/creeper_totem"
                }
            },
            {
                "threshold": 134,
                "model": {
                    "type": "model",
                    "model": "minecraft:item/glitch"
                }
            },
            {
                "threshold": 555,
                "model": {
                    "type": "model",
                    "model": "minecraft:item/villager_totem"
                }
            },
            {
                "threshold": 666,
                "model": {
                    "type": "model",
                    "model": "minecraft:item/infected_totem"
                }
            },
            {
                "threshold": 1000,
                "model": {
                    "type": "model",
                    "model": "minecraft:item/totems/trard"
                }
            },
            {
                "threshold": 1001,
                "model": {
                    "type": "model",
                    "model": "minecraft:item/totems/darkcake"
                }
            },
            {
                "threshold": 1002,
                "model": {
                    "type": "model",
                    "model": "minecraft:item/totems/smipi"
                }
            },
            {
                "threshold": 1003,
                "model": {
                    "type": "model",
                    "model": "minecraft:item/totems/kerito"
                }
            },
            {
                "threshold": 1004,
                "model": {
                    "type": "model",
                    "model": "minecraft:item/totems/fire"
                }
            },
            {
                "threshold": 1005,
                "model": {
                    "type": "model",
                    "model": "minecraft:item/totems/link"
                }
            },
            {
                "threshold": 1006,
                "model": {
                    "type": "model",
                    "model": "minecraft:item/totems/bestytkir"
                }
            },
            {
                "threshold": 1007,
                "model": {
                    "type": "model",
                    "model": "minecraft:item/totems/misterio"
                }
            },
            {
                "threshold": 1008,
                "model": {
                    "type": "model",
                    "model": "minecraft:item/totems/erechi"
                }
            },
            {
                "threshold": 1009,
                "model": {
                    "type": "model",
                    "model": "minecraft:item/totems/slaizteam"
                }
            },
            {
                "threshold": 1010,
                "model": {
                    "type": "model",
                    "model": "minecraft:item/totems/ahi"
                }
            },
            {
                "threshold": 1011,
                "model": {
                    "type": "model",
                    "model": "minecraft:item/totems/mansur"
                }
            },
            {
                "threshold": 1012,
                "model": {
                    "type": "model",
                    "model": "minecraft:item/totems/wasurette"
                }
            },
            {
                "threshold": 1013,
                "model": {
                    "type": "model",
                    "model": "minecraft:item/totems/nezuwa"
                }
            },
            {
                "threshold": 1014,
                "model": {
                    "type": "model",
                    "model": "minecraft:item/totems/terron_"
                }
            },
            {
                "threshold": 1015,
                "model": {
                    "type": "model",
                    "model": "minecraft:item/totems/lestiadmin"
                }
            },
            {
                "threshold": 1016,
                "model": {
                    "type": "model",
                    "model": "minecraft:item/totems/xxanterria_"
                }
            },
            {
                "threshold": 1017,
                "model": {
                    "type": "model",
                    "model": "minecraft:item/totems/thelegwar"
                }
            },
            {
                "threshold": 1018,
                "model": {
                    "type": "model",
                    "model": "minecraft:item/totems/sekyndo4ka"
                }
            },
            {
                "threshold": 1019,
                "model": {
                    "type": "model",
                    "model": "minecraft:item/totems/ynroh"
                }
            },
            {
                "threshold": 1020,
                "model": {
                    "type": "model",
                    "model": "minecraft:item/totems/nullisse"
                }
            },
            {
                "threshold": 1021,
                "model": {
                    "type": "model",
                    "model": "minecraft:item/totems/iwtdie"
                }
            },
            {
                "threshold": 1022,
                "model": {
                    "type": "model",
                    "model": "minecraft:item/totems/ilysanata"
                }
            },
            {
                "threshold": 1023,
                "model": {
                    "type": "model",
                    "model": "minecraft:item/totems/xxanterria"
                }
            },
            {
                "threshold": 1030,
                "model": {
                    "type": "model",
                    "model": "minecraft:item/totems/acivara"
                }
            },
            {
                "threshold": 1031,
                "model": {
                    "type": "model",
                    "model": "minecraft:item/totems/ra7u1"
                }
            },
            {
                "threshold": 1032,
                "model": {
                    "type": "model",
                    "model": "minecraft:item/totems/wernande"
                }
            },
            {
                "threshold": 1033,
                "model": {
                    "type": "model",
                    "model": "minecraft:item/totems/dastasxd"
                }
            },
            {
                "threshold": 1034,
                "model": {
                    "type": "model",
                    "model": "minecraft:item/totems/beeint"
                }
            },
            {
                "threshold": 1035,
                "model": {
                    "type": "model",
                    "model": "minecraft:item/totems/chesee1789"
                }
            },
            {
                "threshold": 1036,
                "model": {
                    "type": "model",
                    "model": "minecraft:item/totems/dan1k091132_"
                }
            },
            {
                "threshold": 1037,
                "model": {
                    "type": "model",
                    "model": "minecraft:item/totems/snapugg"
                }
            },
            {
                "threshold": 1038,
                "model": {
                    "type": "model",
                    "model": "minecraft:item/totems/dang264"
                }
            },
            {
                "threshold": 1039,
                "model": {
                    "type": "model",
                    "model": "minecraft:item/totems/frikbimba"
                }
            },
            {
                "threshold": 1040,
                "model": {
                    "type": "model",
                    "model": "minecraft:item/totems/pars1ze_"
                }
            },
            {
                "threshold": 1041,
                "model": {
                    "type": "model",
                    "model": "minecraft:item/totems/auntmelya"
                }
            },
            {
                "threshold": 1042,
                "model": {
                    "type": "model",
                    "model": "minecraft:item/totems/gghe4kaa"
                }
            },
            {
                "threshold": 1043,
                "model": {
                    "type": "model",
                    "model": "minecraft:item/totems/ogrohin_richard"
                }
            },
            {
                "threshold": 1044,
                "model": {
                    "type": "model",
                    "model": "minecraft:item/totems/trefil_"
                }
            },
            {
                "threshold": 1045,
                "model": {
                    "type": "model",
                    "model": "minecraft:item/totems/scorparri"
                }
            },
            {
                "threshold": 1046,
                "model": {
                    "type": "model",
                    "model": "minecraft:item/totems/googeros"
                }
            },
            {
                "threshold": 1047,
                "model": {
                    "type": "model",
                    "model": "minecraft:item/totems/unkw_source"
                }
            },
            {
                "threshold": 1048,
                "model": {
                    "type": "model",
                    "model": "minecraft:item/totems/conakoo"
                }
            },
            {
                "threshold": 1049,
                "model": {
                    "type": "model",
                    "model": "minecraft:item/totems/sohigtt"
                }
            },
            {
                "threshold": 1050,
                "model": {
                    "type": "model",
                    "model": "minecraft:item/totems/zzshkaa"
                }
            },
            {
                "threshold": 1051,
                "model": {
                    "type": "model",
                    "model": "minecraft:item/totems/glebbomj_"
                }
            },
            {
                "threshold": 1052,
                "model": {
                    "type": "model",
                    "model": "minecraft:item/totems/harqwer1"
                }
            },
            {
                "threshold": 1053,
                "model": {
                    "type": "model",
                    "model": "minecraft:item/totems/kowalskiy"
                }
            },
            {
                "threshold": 1054,
                "model": {
                    "type": "model",
                    "model": "minecraft:item/totems/nezuwa_2d_doll"
                }
            },
            {
                "threshold": 1055,
                "model": {
                    "type": "model",
                    "model": "minecraft:item/totems/wasurette_2d_doll"
                }
            },
            {
                "threshold": 1056,
                "model": {
                    "type": "model",
                    "model": "minecraft:item/totems/trard_2d_doll"
                }
            },
            {
                "threshold": 1057,
                "model": {
                    "type": "model",
                    "model": "minecraft:item/totems/darkcake_2d_doll"
                }
            },
            {
                "threshold": 1058,
                "model": {
                    "type": "model",
                    "model": "minecraft:item/totems/thelegwar_2d_doll"
                }
            },
            {
                "threshold": 1059,
                "model": {
                    "type": "model",
                    "model": "minecraft:item/totems/sekyndo4ka_2d_doll"
                }
            },
            {
                "threshold": 1060,
                "model": {
                    "type": "model",
                    "model": "minecraft:item/totems/ynroh_2d_doll"
                }
            },
            {
                "threshold": 1062,
                "model": {
                    "type": "model",
                    "model": "minecraft:item/totems/bestytkir_2d_doll"
                }
            },
            {
                "threshold": 1063,
                "model": {
                    "type": "model",
                    "model": "minecraft:item/totems/desertykpwq"
                }
            },
            {
                "threshold": 1064,
                "model": {
                    "type": "model",
                    "model": "minecraft:item/totems/mayfol"
                }
            },
            {
                "threshold": 1065,
                "model": {
                    "type": "model",
                    "model": "minecraft:item/totems/pautx"
                }
            },
            {
                "threshold": 1066,
                "model": {
                    "type": "model",
                    "model": "minecraft:item/totems/vioronne"
                }
            },
            {
                "threshold": 1067,
                "model": {
                    "type": "model",
                    "model": "minecraft:item/totems/chel1x"
                }
            },
            {
                "threshold": 1068,
                "model": {
                    "type": "model",
                    "model": "minecraft:item/totems/awieconn"
                }
            },
            {
                "threshold": 1069,
                "model": {
                    "type": "model",
                    "model": "minecraft:item/totems/t0ni42"
                }
            },
            {
                "threshold": 1070,
                "model": {
                    "type": "model",
                    "model": "minecraft:item/totems/erichi_"
                }
            },
            {
                "threshold": 1071,
                "model": {
                    "type": "model",
                    "model": "minecraft:item/totems/im_gayy_"
                }
            },
            {
                "threshold": 1072,
                "model": {
                    "type": "model",
                    "model": "minecraft:item/totems/amethist_play"
                }
            },
            {
                "threshold": 5001,
                "model": {
                    "type": "model",
                    "model": "minecraft:item/eggs/1"
                }
            },
            {
                "threshold": 5002,
                "model": {
                    "type": "model",
                    "model": "minecraft:item/eggs/2"
                }
            },
            {
                "threshold": 5003,
                "model": {
                    "type": "model",
                    "model": "minecraft:item/eggs/3"
                }
            },
            {
                "threshold": 5004,
                "model": {
                    "type": "model",
                    "model": "minecraft:item/eggs/4"
                }
            },
            {
                "threshold": 5005,
                "model": {
                    "type": "model",
                    "model": "minecraft:item/eggs/5"
                }
            },
            {
                "threshold": 5006,
                "model": {
                    "type": "model",
                    "model": "minecraft:item/eggs/6"
                }
            }
        ]
    }
}
